cpp_fwd_sorter/__init__.py
cpp_fwd_sorter/formatter.py
cpp_fwd_sorter/sorter.py
cpp_fwd_sorter-1.0.0.dist-info/licenses/LICENSE
tests/test_smoke.py
tests/test_sorting.py
cpp_fwd_sorter-1.0.0.dist-info/METADATA
cpp_fwd_sorter-1.0.0.dist-info/WHEEL
cpp_fwd_sorter-1.0.0.dist-info/entry_points.txt
cpp_fwd_sorter-1.0.0.dist-info/top_level.txt
cpp_fwd_sorter-1.0.0.dist-info/RECORD
