Metadata-Version: 2.4
Name: cpp-fwd-sorter
Version: 1.0.0
Summary: Sort C++ forward declarations after clang-format
Author: FakeTruth
License: MIT
Project-URL: Homepage, https://github.com/FakeTruth/cpp-fwd-sorter
Project-URL: Source, https://github.com/FakeTruth/cpp-fwd-sorter
Project-URL: BugTracker, https://github.com/FakeTruth/cpp-fwd-sorter/issues
Keywords: clang-format,cpp,forward-declarations,formatter,sorter
Classifier: License :: OSI Approved :: MIT License
Classifier: Programming Language :: Python :: 3
Classifier: Programming Language :: Python :: 3 :: Only
Classifier: Programming Language :: Python :: 3.8
Classifier: Programming Language :: Python :: 3.9
Classifier: Programming Language :: Python :: 3.10
Classifier: Programming Language :: Python :: 3.11
Classifier: Operating System :: OS Independent
Requires-Python: >=3.8
License-File: LICENSE
Provides-Extra: dev
Requires-Dist: pytest>=6.0; extra == "dev"
Dynamic: license-file
